iap_cli/__init__.py
iap_cli/__main__.py
iap_cli/config.py
iap_cli/enums.py
iap_cli/utils.py
iap_cli/commands/__init__.py
iap_cli/commands/app.py
iap_cli/commands/config/__init__.py
iap_cli/commands/config/add.py
iap_cli/commands/config/app.py
iap_cli/commands/get/__init__.py
iap_cli/commands/get/app.py
iap_cli/commands/restart/__init__.py
iap_cli/commands/restart/app.py
iap_cli/models/enums.py
iap_cli/models/iap.py
iap_cli-2024.4a1.dist-info/LICENSE
iap_cli-2024.4a1.dist-info/METADATA
iap_cli-2024.4a1.dist-info/WHEEL
iap_cli-2024.4a1.dist-info/entry_points.txt
iap_cli-2024.4a1.dist-info/top_level.txt
iap_cli-2024.4a1.dist-info/RECORD
