Metadata-Version: 2.1
Name: iap_cli
Version: 2024.4a1
Summary: Lightweight CLI tool to simplify the process of interacting with the Itential Automation Platform.
Home-page: https://github.com/awetomate/itential-iap-cli
Author: John Frauchiger
Author-email: john@awetomate.net
License: MIT
Project-URL: Documentation, https://github.com/awetomate/itential-iap-cli
Project-URL: Source, https://github.com/awetomate/itential-iap-cli
Classifier: Development Status :: 3 - Alpha
Classifier: Intended Audience :: Developers
Classifier: Intended Audience :: Information Technology
Classifier: License :: OSI Approved :: MIT License
Classifier: Operating System :: OS Independent
Classifier: Programming Language :: Python :: 3.9
Classifier: Programming Language :: Python :: 3.10
Classifier: Programming Language :: Python :: 3.11
Classifier: Programming Language :: Python :: 3.12
Classifier: Topic :: Utilities
Requires-Python: >=3.9,<3.12
License-File: LICENSE
Requires-Dist: iap-sdk
Requires-Dist: pydantic <3.0.0,>=2.5.0
Requires-Dist: python-dotenv
Requires-Dist: typer ==0.7.0
Requires-Dist: typer-cli ==0.0.13
Requires-Dist: colorama <0.5.0,>=0.4.3
Requires-Dist: shellingham <2.0.0,>=1.3.0
Requires-Dist: rich <14.0.0,>=10.11.0
